README.md
setup.py
n2o/__init__.py
n2o.egg-info/PKG-INFO
n2o.egg-info/SOURCES.txt
n2o.egg-info/dependency_links.txt
n2o.egg-info/top_level.txt