Metadata-Version: 1.0
Name: n2o
Version: 20.7
Summary: interactive application stack
Home-page: https://github.com/proger/n2o
Author: Vlad Ki
Author-email: proger@hackndev.com
License: MIT
Platform: UNKNOWN
